crucible/__init__.py
crucible/app.py
crucible/context.py
crucible/crucible.tcss
crucible/data/__init__.py
crucible/data/call_filters.py
crucible/data/contract_tree.py
crucible/data/node_filters.py
crucible/data/shadow_tree.py
crucible/data/suite_tree.py
crucible/data/text_styles.py
crucible/data/trace_tree.py
crucible/parser/__init__.py
crucible/parser/compilation.py
crucible/parser/parser.py
crucible/parser/suites.py
crucible/parser/traces.py
crucible/parser/values.py
crucible/runner/__init__.py
crucible/runner/output.py
crucible/runner/protocol.py
crucible/runner/runner.py
crucible/screens/__init__.py
crucible/screens/compilation_results.py
crucible/screens/run_forge_test.py
crucible/screens/run_test_commands.py
crucible/screens/suite.py
crucible/screens/test.py
crucible/screens/tree.py
crucible/suspend.py
forge_crucible-0.1.23.dist-info/METADATA
forge_crucible-0.1.23.dist-info/WHEEL
forge_crucible-0.1.23.dist-info/entry_points.txt
forge_crucible-0.1.23.dist-info/RECORD
